avand/__init__.py
avand/avand.py
avand/decorator.py
avand/exception.py
avand/json_schema.json
avand/response.py
avand/services.json
avand/version.py
avand-1.0.0.dist-info/METADATA
avand-1.0.0.dist-info/WHEEL
avand-1.0.0.dist-info/top_level.txt
avand-1.0.0.dist-info/RECORD
